setup.cfg
setup.py
pyjtech/__init__.py
pyjtech.egg-info/PKG-INFO
pyjtech.egg-info/SOURCES.txt
pyjtech.egg-info/dependency_links.txt
pyjtech.egg-info/top_level.txt
pyjtech.egg-info/zip-safe