Metadata-Version: 1.1
Name: pyjtech
Version: 0.8
Summary: Python3 interface implementation for J-Tech Digital HDMI 2.0 Matrix JTECH-8X8-H20. Also sold by No Hassle AV as the 4K HDMI Matrix 8x8, HDCP2.2
Home-page: https://github.com/netslayer/pyjtech
Author: Chris Germano
Author-email: chris.germano@gmail.com
License: MIT
Download-URL: https://github.com/netslayer/pyjtech/archive/0.8.tar.gz
Platform: UNKNOWN
Classifier: Development Status :: 4 - Beta
Classifier: Programming Language :: Python :: 3.5
